zhonghong_climate/__init__.py
zhonghong_climate/helper.py
zhonghong_climate/hub.py
zhonghong_climate/hvac.py
zhonghong_climate/protocol.py
zhonghong_climate/version.py
zhonghong_climate-1.0.5.dist-info/METADATA
zhonghong_climate-1.0.5.dist-info/WHEEL
zhonghong_climate-1.0.5.dist-info/top_level.txt
zhonghong_climate-1.0.5.dist-info/RECORD
